jockbot_nhl/__init__.py
jockbot_nhl/_helpers.py
jockbot_nhl/config.json
jockbot_nhl/nhl.py
jockbot_nhl-0.0.44.dist-info/LICENSE
jockbot_nhl-0.0.44.dist-info/METADATA
jockbot_nhl-0.0.44.dist-info/WHEEL
jockbot_nhl-0.0.44.dist-info/top_level.txt
jockbot_nhl-0.0.44.dist-info/RECORD
