Metadata-Version: 2.1
Name: jockbot-nhl
Version: 0.0.44
Summary: Retrieve info from NHL API
Home-page: http://github.com/jalgraves/jockbot_nhl
Author: Jonny Graves
Author-email: jalgraves@yahoo.com
License: MIT
License-File: LICENSE
Requires-Dist: pytz
Requires-Dist: requests
